django_createuser/__init__.py
django_createuser/management/__init__.py
django_createuser/management/commands/__init__.py
django_createuser/management/commands/createuser.py
django_createuser-0.1.0.dist-info/LICENSE
django_createuser-0.1.0.dist-info/METADATA
django_createuser-0.1.0.dist-info/WHEEL
django_createuser-0.1.0.dist-info/top_level.txt
django_createuser-0.1.0.dist-info/RECORD
