Metadata-Version: 2.1
Name: django-createuser
Version: 0.1.0
Summary: Create an user for Django
Home-page: https://github.com/dex4er/django-createuser
Author: Piotr Roszatycki
Author-email: piotr.roszatycki@gmail.com
License: LGPL
Keywords: django manage createuser
Platform: OS Independent
Classifier: Development Status :: 3 - Alpha
Classifier: Environment :: Web Environment
Classifier: Intended Audience :: Developers
Classifier: License :: OSI Approved :: GNU Lesser General Public License v3 or later (LGPLv3+)
Classifier: Operating System :: OS Independent
Classifier: Programming Language :: Python
Classifier: Programming Language :: Python :: 2.7
Classifier: Programming Language :: Python :: 3.5
Classifier: Programming Language :: Python :: 3.6
Classifier: Programming Language :: Python :: 3.7
Classifier: Framework :: Django
Classifier: Framework :: Django :: 1.10
Classifier: Framework :: Django :: 1.11
Classifier: Framework :: Django :: 2.0
Classifier: Framework :: Django :: 2.1
Classifier: Framework :: Django :: 2.2
Requires-Dist: django (<2) ; python_version < "3"
Requires-Dist: django (>=2) ; python_version >= "3"
Provides-Extra: dev
Requires-Dist: docutils ; extra == 'dev'
Requires-Dist: Pygments ; extra == 'dev'
